fingerling-1.0.0.dist-info/METADATA
fingerling-1.0.0.dist-info/WHEEL
fingerling-1.0.0.dist-info/license_files/LICENSE
fingerling/__main__.py
fingerling/__init__.py
fingerling/fingerling.cpython-311-x86_64-linux-gnu.so
fingerling-1.0.0.dist-info/RECORD
