Metadata-Version: 2.3
Name: fingerling
Version: 1.0.0
Classifier: Programming Language :: Rust
Classifier: Programming Language :: Python :: Implementation :: CPython
Classifier: Programming Language :: Python :: Implementation :: PyPy
Requires-Dist: maturin >=0.15.0
Requires-Dist: pandas >=2.1
Requires-Dist: numpy >=1.26.4
Requires-Dist: scipy >=1.12.0
License-File: LICENSE
Summary: Support package for Alevin tools. Updated and repackaged version of k3yavi/vpolo
Author-email: Sanskar Jethi <sansyrox@gmail.com>>, Miles Smith <miles-smith@omrf.org>
Requires-Python: >=3.10
Project-URL: homepage, https://github.com/milescsmith/fingerling
Project-URL: repository, https://github.com/milescsmith/fingerling
Project-URL: changelog, https://github.com/milescsmith/fingerling/blob/main/CHANGELOG.md
